nmodels/__init_.py
nmodels/gram.py
nmodels-2.0.2.dist-info/LICENSE
nmodels-2.0.2.dist-info/METADATA
nmodels-2.0.2.dist-info/WHEEL
nmodels-2.0.2.dist-info/top_level.txt
nmodels-2.0.2.dist-info/RECORD
